{"nodes": [{"group": 1, "name": "the"}, {"group": 1, "name": "and"}, {"group": 1, "name": "for"}, {"group": 1, "name": "was"}, {"group": 1, "name": "not"}, {"group": 1, "name": "are"}, {"group": 1, "name": "his"}, {"group": 1, "name": "but"}, {"group": 1, "name": "had"}, {"group": 1, "name": "can"}, {"group": 1, "name": "her"}, {"group": 1, "name": "has"}, {"group": 1, "name": "who"}, {"group": 1, "name": "she"}, {"group": 1, "name": "may"}, {"group": 1, "name": "him"}, {"group": 1, "name": "new"}, {"group": 1, "name": "out"}, {"group": 1, "name": "any"}, {"group": 1, "name": "our"}, {"group": 1, "name": "see"}, {"group": 1, "name": "did"}, {"group": 1, "name": "now"}, {"group": 1, "name": "how"}, {"group": 1, "name": "man"}, {"group": 1, "name": "way"}, {"group": 1, "name": "day"}, {"group": 1, "name": "men"}, {"group": 1, "name": "old"}, {"group": 1, "name": "god"}, {"group": 1, "name": "law"}, {"group": 1, "name": "war"}, {"group": 1, "name": "few"}, {"group": 1, "name": "end"}, {"group": 1, "name": "get"}, {"group": 1, "name": "say"}, {"group": 1, "name": "set"}, {"group": 1, "name": "per"}, {"group": 1, "name": "yet"}, {"group": 1, "name": "far"}, {"group": 1, "name": "act"}, {"group": 1, "name": "put"}, {"group": 1, "name": "let"}, {"group": 1, "name": "why"}, {"group": 1, "name": "age"}, {"group": 1, "name": "air"}, {"group": 1, "name": "low"}, {"group": 1, "name": "nor"}, {"group": 1, "name": "art"}, {"group": 1, "name": "due"}, {"group": 1, "name": "got"}, {"group": 1, "name": "saw"}, {"group": 1, "name": "fig"}, {"group": 1, "name": "non"}, {"group": 1, "name": "six"}, {"group": 1, "name": "son"}, {"group": 1, "name": "sea"}, {"group": 1, "name": "sir"}, {"group": 1, "name": "red"}, {"group": 1, "name": "ten"}, {"group": 1, "name": "vol"}, {"group": 1, "name": "run"}, {"group": 1, "name": "pay"}, {"group": 1, "name": "die"}, {"group": 1, "name": "led"}, {"group": 1, "name": "cut"}, {"group": 1, "name": "job"}, {"group": 1, "name": "big"}, {"group": 1, "name": "iii"}, {"group": 1, "name": "yes"}, {"group": 1, "name": "met"}, {"group": 1, "name": "try"}, {"group": 1, "name": "sun"}, {"group": 1, "name": "bad"}, {"group": 1, "name": "boy"}, {"group": 1, "name": "lay"}, {"group": 1, "name": "der"}, {"group": 1, "name": "bed"}, {"group": 1, "name": "des"}, {"group": 1, "name": "box"}, {"group": 1, "name": "ago"}, {"group": 1, "name": "lot"}, {"group": 1, "name": "add"}, {"group": 1, "name": "gas"}, {"group": 1, "name": "car"}, {"group": 1, "name": "aid"}, {"group": 1, "name": "sex"}, {"group": 1, "name": "sat"}, {"group": 1, "name": "san"}, {"group": 1, "name": "hot"}, {"group": 1, "name": "dry"}, {"group": 1, "name": "van"}, {"group": 1, "name": "bit"}, {"group": 1, "name": "net"}, {"group": 1, "name": "arm"}, {"group": 1, "name": "und"}, {"group": 1, "name": "fit"}, {"group": 1, "name": "sum"}, {"group": 1, "name": "les"}, {"group": 1, "name": "bar"}, {"group": 1, "name": "ran"}, {"group": 1, "name": "pre"}, {"group": 1, "name": "lie"}, {"group": 1, "name": "von"}, {"group": 1, "name": "buy"}, {"group": 1, "name": "thy"}, {"group": 1, "name": "eat"}, {"group": 1, "name": "sit"}, {"group": 1, "name": "dog"}, {"group": 1, "name": "sin"}, {"group": 1, "name": "map"}, {"group": 1, "name": "web"}, {"group": 1, "name": "bay"}, {"group": 1, "name": "que"}, {"group": 1, "name": "won"}, {"group": 1, "name": "mid"}, {"group": 1, "name": "los"}, {"group": 1, "name": "fat"}, {"group": 1, "name": "sky"}, {"group": 1, "name": "sec"}, {"group": 1, "name": "joy"}, {"group": 1, "name": "sub"}, {"group": 1, "name": "via"}, {"group": 1, "name": "hit"}, {"group": 1, "name": "aim"}, {"group": 1, "name": "lee"}, {"group": 1, "name": "vii"}, {"group": 1, "name": "ray"}, {"group": 1, "name": "row"}, {"group": 1, "name": "del"}, {"group": 1, "name": "ear"}, {"group": 1, "name": "cup"}, {"group": 1, "name": "tea"}, {"group": 1, "name": "gun"}, {"group": 1, "name": "win"}, {"group": 1, "name": "raw"}, {"group": 1, "name": "ann"}, {"group": 1, "name": "pro"}, {"group": 1, "name": "fed"}, {"group": 1, "name": "par"}, {"group": 1, "name": "don"}, {"group": 1, "name": "cry"}, {"group": 1, "name": "wet"}, {"group": 1, "name": "leg"}, {"group": 1, "name": "med"}, {"group": 1, "name": "est"}, {"group": 1, "name": "cit"}, {"group": 1, "name": "cat"}, {"group": 1, "name": "hat"}, {"group": 1, "name": "gap"}, {"group": 1, "name": "den"}, {"group": 1, "name": "con"}, {"group": 1, "name": "min"}, {"group": 1, "name": "arc"}, {"group": 1, "name": "ion"}, {"group": 1, "name": "sad"}, {"group": 1, "name": "fun"}, {"group": 1, "name": "fee"}, {"group": 1, "name": "gay"}, {"group": 1, "name": "cap"}, {"group": 1, "name": "guy"}, {"group": 1, "name": "bag"}, {"group": 1, "name": "sam"}, {"group": 1, "name": "log"}, {"group": 1, "name": "bus"}, {"group": 1, "name": "qui"}, {"group": 1, "name": "joe"}, {"group": 1, "name": "soc"}, {"group": 1, "name": "das"}, {"group": 1, "name": "ben"}, {"group": 1, "name": "pan"}, {"group": 1, "name": "jim"}, {"group": 1, "name": "mix"}, {"group": 1, "name": "odd"}, {"group": 1, "name": "fox"}], "links": [{"source": 35, "target": 88, "value": 1}, {"source": 63, "target": 102, "value": 1}, {"source": 29, "target": 50, "value": 1}, {"source": 114, "target": 140, "value": 1}, {"source": 9, "target": 84, "value": 1}, {"source": 84, "target": 147, "value": 1}, {"source": 30, "target": 51, "value": 1}, {"source": 71, "target": 141, "value": 1}, {"source": 8, "target": 148, "value": 1}, {"source": 27, "target": 144, "value": 1}, {"source": 150, "target": 169, "value": 1}, {"source": 13, "target": 20, "value": 1}, {"source": 78, "target": 98, "value": 1}, {"source": 33, "target": 95, "value": 1}, {"source": 96, "target": 123, "value": 1}, {"source": 89, "target": 148, "value": 1}, {"source": 115, "target": 144, "value": 1}, {"source": 87, "target": 107, "value": 1}, {"source": 62, "target": 75, "value": 1}, {"source": 152, "target": 172, "value": 1}, {"source": 2, "target": 47, "value": 1}, {"source": 100, "target": 127, "value": 1}, {"source": 11, "target": 83, "value": 1}, {"source": 147, "target": 159, "value": 1}, {"source": 52, "target": 67, "value": 1}, {"source": 54, "target": 172, "value": 1}, {"source": 130, "target": 139, "value": 1}, {"source": 45, "target": 124, "value": 1}, {"source": 23, "target": 128, "value": 1}, {"source": 8, "target": 155, "value": 1}, {"source": 158, "target": 160, "value": 1}, {"source": 3, "target": 11, "value": 1}, {"source": 26, "target": 168, "value": 1}, {"source": 65, "target": 147, "value": 1}, {"source": 61, "target": 100, "value": 1}, {"source": 1, "target": 33, "value": 1}, {"source": 1, "target": 18, "value": 1}, {"source": 34, "target": 70, "value": 1}, {"source": 143, "target": 163, "value": 1}, {"source": 56, "target": 132, "value": 1}, {"source": 42, "target": 143, "value": 1}, {"source": 72, "target": 97, "value": 1}, {"source": 107, "target": 123, "value": 1}, {"source": 40, "target": 48, "value": 1}, {"source": 83, "target": 158, "value": 1}, {"source": 97, "target": 162, "value": 1}, {"source": 76, "target": 78, "value": 1}, {"source": 123, "target": 146, "value": 1}, {"source": 149, "target": 158, "value": 1}, {"source": 60, "target": 103, "value": 1}, {"source": 64, "target": 98, "value": 1}, {"source": 36, "target": 107, "value": 1}, {"source": 64, "target": 143, "value": 1}, {"source": 53, "target": 151, "value": 1}, {"source": 9, "target": 170, "value": 1}, {"source": 78, "target": 129, "value": 1}, {"source": 49, "target": 113, "value": 1}, {"source": 59, "target": 150, "value": 1}, {"source": 117, "target": 148, "value": 1}, {"source": 110, "target": 159, "value": 1}, {"source": 38, "target": 93, "value": 1}, {"source": 26, "target": 127, "value": 1}, {"source": 14, "target": 26, "value": 1}, {"source": 3, "target": 83, "value": 1}, {"source": 87, "target": 147, "value": 1}, {"source": 61, "target": 156, "value": 1}, {"source": 73, "target": 155, "value": 1}, {"source": 3, "target": 31, "value": 1}, {"source": 55, "target": 140, "value": 1}, {"source": 27, "target": 169, "value": 1}, {"source": 71, "target": 105, "value": 1}, {"source": 74, "target": 104, "value": 1}, {"source": 36, "target": 70, "value": 1}, {"source": 34, "target": 50, "value": 1}, {"source": 27, "target": 70, "value": 1}, {"source": 9, "target": 159, "value": 1}, {"source": 32, "target": 157, "value": 1}, {"source": 119, "target": 167, "value": 1}, {"source": 70, "target": 142, "value": 1}, {"source": 66, "target": 166, "value": 1}, {"source": 42, "target": 70, "value": 1}, {"source": 55, "target": 72, "value": 1}, {"source": 88, "target": 100, "value": 1}, {"source": 69, "target": 78, "value": 1}, {"source": 57, "target": 109, "value": 1}, {"source": 44, "target": 80, "value": 1}, {"source": 7, "target": 92, "value": 1}, {"source": 42, "target": 98, "value": 1}, {"source": 30, "target": 135, "value": 1}, {"source": 23, "target": 89, "value": 1}, {"source": 39, "target": 99, "value": 1}, {"source": 103, "target": 151, "value": 1}, {"source": 1, "target": 95, "value": 1}, {"source": 15, "target": 123, "value": 1}, {"source": 84, "target": 130, "value": 1}, {"source": 4, "target": 81, "value": 1}, {"source": 30, "target": 75, "value": 1}, {"source": 81, "target": 163, "value": 1}, {"source": 32, "target": 138, "value": 1}, {"source": 39, "target": 139, "value": 1}, {"source": 5, "target": 101, "value": 1}, {"source": 91, "target": 103, "value": 1}, {"source": 51, "target": 162, "value": 1}, {"source": 64, "target": 138, "value": 1}, {"source": 56, "target": 86, "value": 1}, {"source": 82, "target": 85, "value": 1}, {"source": 87, "target": 88, "value": 1}, {"source": 38, "target": 70, "value": 1}, {"source": 103, "target": 140, "value": 1}, {"source": 4, "target": 50, "value": 1}, {"source": 20, "target": 125, "value": 1}, {"source": 12, "target": 43, "value": 1}, {"source": 36, "target": 56, "value": 1}, {"source": 9, "target": 147, "value": 1}, {"source": 123, "target": 148, "value": 1}, {"source": 25, "target": 31, "value": 1}, {"source": 106, "target": 147, "value": 1}, {"source": 87, "target": 148, "value": 1}, {"source": 146, "target": 147, "value": 1}, {"source": 62, "target": 158, "value": 1}, {"source": 7, "target": 104, "value": 1}, {"source": 25, "target": 43, "value": 1}, {"source": 72, "target": 109, "value": 1}, {"source": 35, "target": 87, "value": 1}, {"source": 16, "target": 22, "value": 1}, {"source": 115, "target": 172, "value": 1}, {"source": 46, "target": 128, "value": 1}, {"source": 104, "target": 112, "value": 1}, {"source": 17, "target": 41, "value": 1}, {"source": 50, "target": 89, "value": 1}, {"source": 14, "target": 24, "value": 1}, {"source": 26, "target": 158, "value": 1}, {"source": 72, "target": 156, "value": 1}, {"source": 77, "target": 169, "value": 1}, {"source": 42, "target": 93, "value": 1}, {"source": 102, "target": 125, "value": 1}, {"source": 35, "target": 118, "value": 1}, {"source": 94, "target": 124, "value": 1}, {"source": 10, "target": 76, "value": 1}, {"source": 9, "target": 88, "value": 1}, {"source": 35, "target": 162, "value": 1}, {"source": 22, "target": 23, "value": 1}, {"source": 14, "target": 112, "value": 1}, {"source": 61, "target": 72, "value": 1}, {"source": 26, "target": 90, "value": 1}, {"source": 74, "target": 112, "value": 1}, {"source": 84, "target": 159, "value": 1}, {"source": 34, "target": 42, "value": 1}, {"source": 15, "target": 124, "value": 1}, {"source": 106, "target": 117, "value": 1}, {"source": 35, "target": 51, "value": 1}, {"source": 21, "target": 115, "value": 1}, {"source": 45, "target": 57, "value": 1}, {"source": 96, "target": 146, "value": 1}, {"source": 35, "target": 127, "value": 1}, {"source": 66, "target": 120, "value": 1}, {"source": 58, "target": 77, "value": 1}, {"source": 98, "target": 125, "value": 1}, {"source": 27, "target": 59, "value": 1}, {"source": 6, "target": 11, "value": 1}, {"source": 4, "target": 47, "value": 1}, {"source": 22, "target": 46, "value": 1}, {"source": 4, "target": 53, "value": 1}, {"source": 51, "target": 87, "value": 1}, {"source": 88, "target": 170, "value": 1}, {"source": 73, "target": 161, "value": 1}, {"source": 106, "target": 145, "value": 1}, {"source": 88, "target": 109, "value": 1}, {"source": 112, "target": 158, "value": 1}, {"source": 31, "target": 99, "value": 1}, {"source": 62, "target": 112, "value": 1}, {"source": 25, "target": 62, "value": 1}, {"source": 98, "target": 116, "value": 1}, {"source": 122, "target": 126, "value": 1}, {"source": 4, "target": 22, "value": 1}, {"source": 18, "target": 136, "value": 1}, {"source": 53, "target": 140, "value": 1}, {"source": 75, "target": 112, "value": 1}, {"source": 48, "target": 94, "value": 1}, {"source": 84, "target": 139, "value": 1}, {"source": 56, "target": 119, "value": 1}, {"source": 26, "target": 112, "value": 1}, {"source": 9, "target": 24, "value": 1}, {"source": 55, "target": 88, "value": 1}, {"source": 70, "target": 144, "value": 1}, {"source": 39, "target": 130, "value": 1}, {"source": 139, "target": 170, "value": 1}, {"source": 27, "target": 152, "value": 1}, {"source": 51, "target": 135, "value": 1}, {"source": 104, "target": 160, "value": 1}, {"source": 8, "target": 73, "value": 1}, {"source": 87, "target": 117, "value": 1}, {"source": 58, "target": 144, "value": 1}, {"source": 14, "target": 35, "value": 1}, {"source": 69, "target": 98, "value": 1}, {"source": 34, "target": 93, "value": 1}, {"source": 97, "target": 121, "value": 1}, {"source": 24, "target": 91, "value": 1}, {"source": 79, "target": 174, "value": 1}, {"source": 11, "target": 168, "value": 1}, {"source": 17, "target": 65, "value": 1}, {"source": 133, "target": 160, "value": 1}, {"source": 54, "target": 107, "value": 1}, {"source": 64, "target": 125, "value": 1}, {"source": 90, "target": 141, "value": 1}, {"source": 109, "target": 152, "value": 1}, {"source": 58, "target": 64, "value": 1}, {"source": 1, "target": 82, "value": 1}, {"source": 24, "target": 170, "value": 1}, {"source": 114, "target": 134, "value": 1}, {"source": 125, "target": 143, "value": 1}, {"source": 107, "target": 109, "value": 1}, {"source": 103, "target": 154, "value": 1}, {"source": 54, "target": 86, "value": 1}, {"source": 8, "target": 11, "value": 1}, {"source": 7, "target": 164, "value": 1}, {"source": 24, "target": 110, "value": 1}, {"source": 106, "target": 148, "value": 1}, {"source": 72, "target": 133, "value": 1}, {"source": 27, "target": 150, "value": 1}, {"source": 5, "target": 94, "value": 1}, {"source": 82, "target": 173, "value": 1}, {"source": 99, "target": 161, "value": 1}, {"source": 0, "target": 13, "value": 1}, {"source": 31, "target": 130, "value": 1}, {"source": 127, "target": 158, "value": 1}, {"source": 39, "target": 117, "value": 1}, {"source": 75, "target": 158, "value": 1}, {"source": 5, "target": 44, "value": 1}, {"source": 92, "target": 96, "value": 1}, {"source": 20, "target": 157, "value": 1}, {"source": 36, "target": 87, "value": 1}, {"source": 42, "target": 142, "value": 1}, {"source": 28, "target": 173, "value": 1}, {"source": 4, "target": 93, "value": 1}, {"source": 51, "target": 88, "value": 1}, {"source": 112, "target": 127, "value": 1}, {"source": 24, "target": 27, "value": 1}, {"source": 25, "target": 26, "value": 1}, {"source": 149, "target": 159, "value": 1}, {"source": 87, "target": 155, "value": 1}, {"source": 111, "target": 142, "value": 1}, {"source": 53, "target": 103, "value": 1}, {"source": 31, "target": 139, "value": 1}, {"source": 127, "target": 135, "value": 1}, {"source": 92, "target": 107, "value": 1}, {"source": 73, "target": 99, "value": 1}, {"source": 22, "target": 128, "value": 1}, {"source": 35, "target": 158, "value": 1}, {"source": 9, "target": 151, "value": 1}, {"source": 155, "target": 162, "value": 1}, {"source": 55, "target": 151, "value": 1}, {"source": 62, "target": 127, "value": 1}, {"source": 14, "target": 75, "value": 1}, {"source": 9, "target": 91, "value": 1}, {"source": 30, "target": 46, "value": 1}, {"source": 77, "target": 138, "value": 1}, {"source": 16, "target": 32, "value": 1}, {"source": 116, "target": 163, "value": 1}, {"source": 120, "target": 166, "value": 1}, {"source": 24, "target": 152, "value": 1}, {"source": 48, "target": 153, "value": 1}, {"source": 55, "target": 103, "value": 1}, {"source": 53, "target": 154, "value": 1}, {"source": 87, "target": 106, "value": 1}, {"source": 140, "target": 154, "value": 1}, {"source": 88, "target": 155, "value": 1}, {"source": 73, "target": 112, "value": 1}, {"source": 7, "target": 17, "value": 1}, {"source": 39, "target": 84, "value": 1}, {"source": 36, "target": 42, "value": 1}, {"source": 10, "target": 37, "value": 1}, {"source": 34, "target": 38, "value": 1}, {"source": 14, "target": 158, "value": 1}, {"source": 103, "target": 114, "value": 1}, {"source": 98, "target": 143, "value": 1}, {"source": 62, "target": 170, "value": 1}, {"source": 151, "target": 154, "value": 1}, {"source": 58, "target": 138, "value": 1}, {"source": 42, "target": 64, "value": 1}, {"source": 53, "target": 114, "value": 1}, {"source": 25, "target": 158, "value": 1}, {"source": 65, "target": 146, "value": 1}, {"source": 5, "target": 153, "value": 1}, {"source": 26, "target": 62, "value": 1}, {"source": 91, "target": 100, "value": 1}, {"source": 25, "target": 35, "value": 1}, {"source": 6, "target": 15, "value": 1}, {"source": 2, "target": 39, "value": 1}, {"source": 14, "target": 127, "value": 1}, {"source": 75, "target": 127, "value": 1}, {"source": 26, "target": 75, "value": 1}, {"source": 110, "target": 149, "value": 1}, {"source": 35, "target": 155, "value": 1}, {"source": 71, "target": 90, "value": 1}, {"source": 64, "target": 77, "value": 1}, {"source": 36, "target": 142, "value": 1}, {"source": 1, "target": 136, "value": 1}, {"source": 89, "target": 123, "value": 1}, {"source": 11, "target": 148, "value": 1}, {"source": 9, "target": 100, "value": 1}, {"source": 108, "target": 163, "value": 1}, {"source": 3, "target": 25, "value": 1}, {"source": 37, "target": 76, "value": 1}, {"source": 43, "target": 105, "value": 1}, {"source": 26, "target": 35, "value": 1}, {"source": 24, "target": 88, "value": 1}, {"source": 81, "target": 89, "value": 1}, {"source": 94, "target": 153, "value": 1}, {"source": 59, "target": 169, "value": 1}, {"source": 78, "target": 168, "value": 1}, {"source": 117, "target": 147, "value": 1}, {"source": 25, "target": 112, "value": 1}, {"source": 72, "target": 88, "value": 1}, {"source": 36, "target": 38, "value": 1}, {"source": 24, "target": 100, "value": 1}, {"source": 31, "target": 84, "value": 1}, {"source": 55, "target": 114, "value": 1}, {"source": 104, "target": 164, "value": 1}, {"source": 100, "target": 170, "value": 1}, {"source": 57, "target": 107, "value": 1}, {"source": 76, "target": 129, "value": 1}, {"source": 21, "target": 85, "value": 1}, {"source": 21, "target": 63, "value": 1}, {"source": 20, "target": 36, "value": 1}, {"source": 68, "target": 126, "value": 1}, {"source": 72, "target": 121, "value": 1}, {"source": 73, "target": 77, "value": 1}, {"source": 54, "target": 57, "value": 1}, {"source": 129, "target": 150, "value": 1}, {"source": 81, "target": 116, "value": 1}, {"source": 59, "target": 132, "value": 1}, {"source": 88, "target": 162, "value": 1}, {"source": 34, "target": 142, "value": 1}, {"source": 83, "target": 149, "value": 1}, {"source": 20, "target": 86, "value": 1}, {"source": 7, "target": 65, "value": 1}, {"source": 49, "target": 63, "value": 1}, {"source": 62, "target": 139, "value": 1}, {"source": 92, "target": 123, "value": 1}, {"source": 6, "target": 123, "value": 1}, {"source": 76, "target": 150, "value": 1}, {"source": 99, "target": 130, "value": 1}, {"source": 70, "target": 93, "value": 1}, {"source": 47, "target": 53, "value": 1}, {"source": 131, "target": 159, "value": 1}, {"source": 93, "target": 142, "value": 1}, {"source": 34, "target": 36, "value": 1}, {"source": 7, "target": 41, "value": 1}, {"source": 20, "target": 119, "value": 1}, {"source": 91, "target": 170, "value": 1}, {"source": 85, "target": 115, "value": 1}, {"source": 101, "target": 137, "value": 1}, {"source": 46, "target": 81, "value": 1}, {"source": 96, "target": 117, "value": 1}, {"source": 124, "target": 171, "value": 1}, {"source": 35, "target": 75, "value": 1}, {"source": 77, "target": 144, "value": 1}, {"source": 112, "target": 161, "value": 1}, {"source": 96, "target": 107, "value": 1}, {"source": 138, "target": 157, "value": 1}, {"source": 114, "target": 151, "value": 1}, {"source": 25, "target": 75, "value": 1}, {"source": 92, "target": 146, "value": 1}, {"source": 35, "target": 62, "value": 1}, {"source": 99, "target": 139, "value": 1}, {"source": 74, "target": 79, "value": 1}, {"source": 4, "target": 89, "value": 1}, {"source": 0, "target": 105, "value": 1}, {"source": 107, "target": 146, "value": 1}, {"source": 85, "target": 124, "value": 1}, {"source": 109, "target": 134, "value": 1}, {"source": 55, "target": 154, "value": 1}, {"source": 35, "target": 112, "value": 1}, {"source": 42, "target": 125, "value": 1}, {"source": 55, "target": 109, "value": 1}, {"source": 113, "target": 165, "value": 1}, {"source": 65, "target": 131, "value": 1}, {"source": 125, "target": 157, "value": 1}, {"source": 53, "target": 55, "value": 1}, {"source": 3, "target": 168, "value": 1}, {"source": 14, "target": 110, "value": 1}, {"source": 147, "target": 148, "value": 1}, {"source": 106, "target": 130, "value": 1}, {"source": 83, "target": 168, "value": 1}, {"source": 14, "target": 25, "value": 1}, {"source": 38, "target": 42, "value": 1}, {"source": 52, "target": 96, "value": 1}, {"source": 20, "target": 56, "value": 1}, {"source": 128, "target": 135, "value": 1}, {"source": 15, "target": 171, "value": 1}, {"source": 55, "target": 167, "value": 1}, {"source": 115, "target": 152, "value": 1}, {"source": 25, "target": 127, "value": 1}, {"source": 88, "target": 91, "value": 1}, {"source": 50, "target": 81, "value": 1}, {"source": 38, "target": 142, "value": 1}, {"source": 54, "target": 109, "value": 1}, {"source": 46, "target": 163, "value": 1}, {"source": 64, "target": 144, "value": 1}, {"source": 140, "target": 150, "value": 1}, {"source": 22, "target": 53, "value": 1}, {"source": 78, "target": 150, "value": 1}, {"source": 100, "target": 135, "value": 1}, {"source": 2, "target": 174, "value": 1}, {"source": 138, "target": 144, "value": 1}, {"source": 14, "target": 62, "value": 1}, {"source": 22, "target": 47, "value": 1}, {"source": 114, "target": 154, "value": 1}, {"source": 74, "target": 120, "value": 1}, {"source": 23, "target": 46, "value": 1}, {"source": 36, "target": 86, "value": 1}, {"source": 99, "target": 112, "value": 1}, {"source": 108, "target": 140, "value": 1}, {"source": 67, "target": 161, "value": 1}, {"source": 51, "target": 155, "value": 1}, {"source": 87, "target": 162, "value": 1}, {"source": 67, "target": 92, "value": 1}, {"source": 134, "target": 152, "value": 1}, {"source": 61, "target": 133, "value": 1}, {"source": 86, "target": 119, "value": 1}, {"source": 84, "target": 99, "value": 1}, {"source": 36, "target": 119, "value": 1}, {"source": 38, "target": 69, "value": 1}, {"source": 36, "target": 93, "value": 1}, {"source": 1, "target": 85, "value": 1}, {"source": 17, "target": 19, "value": 1}, {"source": 31, "target": 39, "value": 1}, {"source": 5, "target": 48, "value": 1}, {"source": 46, "target": 116, "value": 1}, {"source": 133, "target": 156, "value": 1}, {"source": 140, "target": 151, "value": 1}, {"source": 41, "target": 65, "value": 1}, {"source": 42, "target": 81, "value": 1}, {"source": 37, "target": 139, "value": 1}, {"source": 16, "target": 93, "value": 1}, {"source": 45, "target": 85, "value": 1}]}